valkyrie_tools/__init__.py
valkyrie_tools/cache.py
valkyrie_tools/commons.py
valkyrie_tools/config.py
valkyrie_tools/constants.py
valkyrie_tools/dns.py
valkyrie_tools/dnscheck.py
valkyrie_tools/exceptions.py
valkyrie_tools/files.py
valkyrie_tools/httpr.py
valkyrie_tools/ipaddr.py
valkyrie_tools/ipcheck.py
valkyrie_tools/logger.py
valkyrie_tools/urlcheck.py
valkyrie_tools/valkyrie.py
valkyrie_tools/whobe.py
valkyrie_tools/whois.py
valkyrie_tools-1.3.1.dist-info/LICENSE
valkyrie_tools-1.3.1.dist-info/METADATA
valkyrie_tools-1.3.1.dist-info/WHEEL
valkyrie_tools-1.3.1.dist-info/entry_points.txt
valkyrie_tools-1.3.1.dist-info/RECORD
