Metadata-Version: 2.1
Name: valkyrie-tools
Version: 1.3.1
Summary: Valkyrie Tools
Home-page: https://github.com/xransum/valkyrie-tools
License: MIT
Author: xransum
Author-email: xransum@users.noreply.github.com
Requires-Python: >=3.8,<4.0
Classifier: License :: OSI Approved :: MIT License
Classifier: Programming Language :: Python :: 3
Classifier: Programming Language :: Python :: 3.8
Classifier: Programming Language :: Python :: 3.9
Classifier: Programming Language :: Python :: 3.10
Classifier: Programming Language :: Python :: 3.11
Classifier: Programming Language :: Python :: 3.12
Requires-Dist: appdirs (>=1.4.4,<2.0.0)
Requires-Dist: art (>=6.1,<7.0)
Requires-Dist: beautifulsoup4 (>=4.12.2,<5.0.0)
Requires-Dist: click (>=7.0)
Requires-Dist: ipwhois (>=1.2.0,<2.0.0)
Requires-Dist: nox (>=2020.8.22)
Requires-Dist: nox-poetry (>=1.0.3,<2.0.0)
Requires-Dist: packaging (>=20.9)
Requires-Dist: pexpect (>=4.8.0,<5.0.0)
Requires-Dist: python-whois (>=0.8.0,<0.9.0)
Requires-Dist: sphinx-click (>=5.0.1,<6.0.0)
Requires-Dist: sphinx-rtd-theme (>=1.3.0,<2.0.0)
Requires-Dist: tomlkit (>=0.7)
Requires-Dist: types-beautifulsoup4 (>=4.12.0,<5.0.0)
Requires-Dist: types-requests (>=2.31.0,<3.0.0)
Requires-Dist: validators (>=0.22.0,<0.23.0)
Project-URL: Changelog, https://github.com/xransum/valkyrie-tools/releases
Project-URL: Documentation, https://valkyrie-tools.readthedocs.io
Project-URL: Repository, https://github.com/xransum/valkyrie-tools
